MANIFEST.in
README.txt
setup.cfg
setup.py
docs/HISTORY.txt
docs/INSTALL.txt
docs/LICENSE.GPL
docs/LICENSE.txt
ityou/__init__.py
ityou.astream.egg-info/PKG-INFO
ityou.astream.egg-info/SOURCES.txt
ityou.astream.egg-info/dependency_links.txt
ityou.astream.egg-info/entry_points.txt
ityou.astream.egg-info/namespace_packages.txt
ityou.astream.egg-info/not-zip-safe
ityou.astream.egg-info/paster_plugins.txt
ityou.astream.egg-info/requires.txt
ityou.astream.egg-info/top_level.txt
ityou/astream/__init__.py
ityou/astream/activity_event_handler.py
ityou/astream/config.py
ityou/astream/configure.zcml
ityou/astream/db_tests.py
ityou/astream/dbapi.py
ityou/astream/interfaces.py
ityou/astream/tests.py
ityou/astream/translate.sh
ityou/astream/viewlets.py
ityou/astream/Extensions/Install.py
ityou/astream/Extensions/__init__.py
ityou/astream/browser/__init__.py
ityou/astream/browser/activities.py
ityou/astream/browser/configure.zcml
ityou/astream/browser/controlpanel.py
ityou/astream/browser/images/button-hover.png
ityou/astream/browser/images/button.png
ityou/astream/browser/images/eye-close.png
ityou/astream/browser/images/ityou-esi-astream-icon.png
ityou/astream/browser/javascripts/.placeholder
ityou/astream/browser/stylesheets/astream.css
ityou/astream/browser/templates/activities.pt
ityou/astream/browser/templates/astream_viewlet.pt
ityou/astream/browser/templates/macros.pt
ityou/astream/browser/templates/tmpl-macros.pt
ityou/astream/guides/ITYOU_ESI_GUIDE.py
ityou/astream/guides/__init__.py
ityou/astream/locales/ityou.astream.pot
ityou/astream/locales/plone.pot
ityou/astream/locales (Kopie)/ityou.astream.pot
ityou/astream/locales (Kopie)/plone.pot
ityou/astream/locales (Kopie)/de/LC_MESSAGES/ityou.astream.po
ityou/astream/locales (Kopie)/de/LC_MESSAGES/plone.po
ityou/astream/locales (Kopie)/en/LC_MESSAGES/ityou.astream.po
ityou/astream/locales (Kopie)/en/LC_MESSAGES/plone.po
ityou/astream/locales/de/LC_MESSAGES/ityou.astream.po
ityou/astream/locales/de/LC_MESSAGES/plone.po
ityou/astream/locales/en/LC_MESSAGES/ityou.astream.po
ityou/astream/locales/en/LC_MESSAGES/plone.po
ityou/astream/profiles/default/browserlayer.xml
ityou/astream/profiles/default/controlpanel.xml
ityou/astream/profiles/default/cssregistry.xml
ityou/astream/profiles/default/jsregistry.xml
ityou/astream/profiles/default/metadata.xml
