Metadata-Version: 1.1
Name: ityou.astream
Version: 1.3.1
Summary: Activity Stream for ITYOU ESI
Home-page: http://www.ityou.de/esi/
Author: ITYOU/LM
Author-email: lm@ityou.de
License: GPL
Keywords: plone,social,activity stream
Platform: UNKNOWN
Classifier: Framework :: Plone
Classifier: Programming Language :: Python
